ProgramizCYuyanJiaochengChuyi/README.md
ProgramizCYuyanJiaochengChuyi/__init__.py
ProgramizCYuyanJiaochengChuyi/__main__.py
ProgramizCYuyanJiaochengChuyi/file.epub
ProgramizCYuyanJiaochengChuyi/index.html
ProgramizCYuyanJiaochengChuyi/css/__init__.py
ProgramizCYuyanJiaochengChuyi/css/annotations.css
ProgramizCYuyanJiaochengChuyi/css/main.css
ProgramizCYuyanJiaochengChuyi/css/normalize.css
ProgramizCYuyanJiaochengChuyi/css/popup.css
ProgramizCYuyanJiaochengChuyi/font/__init__.py
ProgramizCYuyanJiaochengChuyi/font/fontello.eot
ProgramizCYuyanJiaochengChuyi/font/fontello.svg
ProgramizCYuyanJiaochengChuyi/font/fontello.ttf
ProgramizCYuyanJiaochengChuyi/font/fontello.woff
ProgramizCYuyanJiaochengChuyi/img/__init__.py
ProgramizCYuyanJiaochengChuyi/img/annotator-glyph-sprite.png
ProgramizCYuyanJiaochengChuyi/img/annotator-icon-sprite.png
ProgramizCYuyanJiaochengChuyi/img/apple-touch-icon.png
ProgramizCYuyanJiaochengChuyi/img/cancelfullscreen.png
ProgramizCYuyanJiaochengChuyi/img/close.png
ProgramizCYuyanJiaochengChuyi/img/fullscreen.png
ProgramizCYuyanJiaochengChuyi/img/loader.gif
ProgramizCYuyanJiaochengChuyi/img/menu-icon.png
ProgramizCYuyanJiaochengChuyi/img/save.png
ProgramizCYuyanJiaochengChuyi/img/saved.png
ProgramizCYuyanJiaochengChuyi/img/settings-s.png
ProgramizCYuyanJiaochengChuyi/img/settings.png
ProgramizCYuyanJiaochengChuyi/img/star.png
ProgramizCYuyanJiaochengChuyi/js/__init__.py
ProgramizCYuyanJiaochengChuyi/js/epub.js
ProgramizCYuyanJiaochengChuyi/js/epub.min.js
ProgramizCYuyanJiaochengChuyi/js/epub.min.map
ProgramizCYuyanJiaochengChuyi/js/hooks.min.js
ProgramizCYuyanJiaochengChuyi/js/hooks.min.map
ProgramizCYuyanJiaochengChuyi/js/reader.js
ProgramizCYuyanJiaochengChuyi/js/reader.js.map
ProgramizCYuyanJiaochengChuyi/js/reader.min.js
ProgramizCYuyanJiaochengChuyi/js/reader.min.map
ProgramizCYuyanJiaochengChuyi/js/hooks/__init__.py
ProgramizCYuyanJiaochengChuyi/js/hooks/extensions/__init__.py
ProgramizCYuyanJiaochengChuyi/js/hooks/extensions/highlight.js
programiz_c_yuyan_jiaocheng_chuyi-2024.3.5.0.dist-info/METADATA
programiz_c_yuyan_jiaocheng_chuyi-2024.3.5.0.dist-info/WHEEL
programiz_c_yuyan_jiaocheng_chuyi-2024.3.5.0.dist-info/entry_points.txt
programiz_c_yuyan_jiaocheng_chuyi-2024.3.5.0.dist-info/top_level.txt
programiz_c_yuyan_jiaocheng_chuyi-2024.3.5.0.dist-info/RECORD
